classy.cpython-38-darwin.so
classy/bbn/sBBN_2017.dat
classy/bbn/sBBN.dat
classy/bbn/sBBN_2017_marcucci.dat
classy/hyrec/history.c
classy/hyrec/R_inf.dat
classy/hyrec/helium.h
classy/hyrec/hyrectools.c
classy/hyrec/hydrogen.h
classy/hyrec/hyrec.c
classy/hyrec/two_photon_tables.dat
classy/hyrec/helium.c
classy/hyrec/history.h
classy/hyrec/hydrogen.c
classy/hyrec/hyrectools.h
classy/hyrec/input.dat
classy/hyrec/Alpha_inf.dat
classy/hyrec/hyrec.h
classy_community-23.2.0.dist-info/COPYING.txt
classy_community-23.2.0.dist-info/RECORD
classy_community-23.2.0.dist-info/WHEEL
classy_community-23.2.0.dist-info/top_level.txt
classy_community-23.2.0.dist-info/LICENSE.txt
classy_community-23.2.0.dist-info/AUTHORS.txt
classy_community-23.2.0.dist-info/METADATA
