Metadata-Version: 2.1
Name: classy-community
Version: 23.2.0
Summary: Python interface to the C++ community-edition of the cosmological Boltzmann code CLASS
Author-email: Thomas Tram <thomas.tram@phys.au.dk>
Project-URL: Homepage, https://github.com/AarhusCosmology/CLASSpp_public
Project-URL: Bug Tracker, https://github.com/AarhusCosmology/CLASSpp_public/issues
Classifier: Programming Language :: Python :: 3
Classifier: License :: OSI Approved :: GNU General Public License v3 (GPLv3)
Classifier: Operating System :: OS Independent
Requires-Python: >=3.7
License-File: LICENSE.txt
License-File: COPYING.txt
License-File: AUTHORS.txt
